pymmep/README.md
pymmep/__init__.py
pymmep/container.py
pymmep/container_utils.py
pymmep/eaf_container.py
pymmep/eaf_utils.py
pymmep-0.2.0.dist-info/METADATA
pymmep-0.2.0.dist-info/WHEEL
pymmep-0.2.0.dist-info/RECORD
